funcpck
